{"name":"createVoucherEntryUsingSustainabilityAccounts","id":"org.icrc.fadapplic.IRIS.FAD.AccountsPayable.VoucherEntries:createVoucherEntryUsingSustainabilityAccounts","testCaseName":"org.icrc.fadapplic.IRIS.FAD.AccountsPayable.VoucherEntries","testSteps":[{"number":1,"description":"Given that I\u0027m logged in to Voucher Entry page","duration":39397,"startTime":"2023-02-21T16:20:42.979+08:00[Asia/Shanghai]","screenshots":[{"screenshot":"edf8a77366496d7b80525a62a18d0a48c941a46fe9fc99e14d6b7bb31fed5f2a.png","timeStamp":1676967682376}],"result":"SUCCESS","precondition":false,"level":0,"children":[{"number":2,"description":"When i open FAD URL","duration":33622,"startTime":"2023-02-21T16:20:42.980+08:00[Asia/Shanghai]","screenshots":[{"screenshot":"6c8ff540379982290e99e0001b7baf1824d1a06172ed11ec2755e66e8176a55f.png","timeStamp":1676967676602}],"result":"SUCCESS","precondition":false,"level":1},{"number":3,"description":"When i open page from sidebar menu: {Accounts Payable,Voucher Entries,Voucher Entry}","duration":5762,"startTime":"2023-02-21T16:21:16.603+08:00[Asia/Shanghai]","screenshots":[{"screenshot":"6c8ff540379982290e99e0001b7baf1824d1a06172ed11ec2755e66e8176a55f.png","timeStamp":1676967676618},{"screenshot":"a8047730710383785acef50e5c00d445fad24f8eb0cca72731f68cc1bc6bb4d1.png","timeStamp":1676967677511},{"screenshot":"d1d692cab5701f0347c3f03d8ecef457d1b1b528df361705907c0523e310774a.png","timeStamp":1676967678250},{"screenshot":"0d3d70965bcbdb641091755199f8a303b2ea1715001c29d8a5d9098b0d9660fb.png","timeStamp":1676967679060},{"screenshot":"edf8a77366496d7b80525a62a18d0a48c941a46fe9fc99e14d6b7bb31fed5f2a.png","timeStamp":1676967682365}],"result":"SUCCESS","precondition":false,"level":1}]},{"number":4,"description":"Then the Payment Information form and its contents should show up","duration":376,"startTime":"2023-02-21T16:21:22.376+08:00[Asia/Shanghai]","screenshots":[{"screenshot":"d7e59e2fd40a6c1686f08bba0b7158c04595740423b88047dc1b6ae39fd68796.png","timeStamp":1676967682752}],"result":"SUCCESS","precondition":false,"level":0},{"number":5,"description":"When I set the Supplier to \u0027133339\u0027","duration":4848,"startTime":"2023-02-21T16:21:22.753+08:00[Asia/Shanghai]","screenshots":[{"screenshot":"2272d3f153fee5f5fc7dc577cb716f338461bd928d0d2cfe663281ee0445900a.png","timeStamp":1676967685391},{"screenshot":"49682f9db7964f323a1a3f022231dbf13a63466f6341ced67dd87c51f14d3802.png","timeStamp":1676967687601}],"result":"SUCCESS","precondition":false,"level":0},{"number":6,"description":"When I set the \u0027Invouce Number\u0027 to \u0027pcBjIKWIMS\u0027","duration":685,"startTime":"2023-02-21T16:21:27.601+08:00[Asia/Shanghai]","screenshots":[{"screenshot":"0a9deb001ee2818eeaccf4440c19f1567b2aea64bbd70f654b06df01105aaec7.png","timeStamp":1676967688286}],"result":"SUCCESS","precondition":false,"level":0},{"number":7,"description":"When I set the Currency to \u0027USD\u0027","duration":4765,"startTime":"2023-02-21T16:21:28.287+08:00[Asia/Shanghai]","screenshots":[{"screenshot":"1f0de2bfdacddfe2209e007e4ecb086ae2f114f9f2961730e209133dd82ef25e.png","timeStamp":1676967691769},{"screenshot":"0ecbcaf3f2a13964c4ffd58e53354d7db06070af860a8cf41551effa7ce82645.png","timeStamp":1676967693052}],"result":"SUCCESS","precondition":false,"level":0},{"number":8,"description":"When i click on continue button","duration":2084,"startTime":"2023-02-21T16:21:33.053+08:00[Asia/Shanghai]","screenshots":[{"screenshot":"f1c80aa685b12b4a343f57e1cfcf7fad756a20350b7ede79368bacbf68b7ba6b.png","timeStamp":1676967693684},{"screenshot":"f630d541946969a9bb7e60e87d41d29bcb5ace5315b7fa1d5b1eb2de47d1dd44.png","timeStamp":1676967695137}],"result":"SUCCESS","precondition":false,"level":0},{"number":9,"description":"When I select the first Bank Account and click \u0027Submit\u0027 button if modal exist","duration":33903,"startTime":"2023-02-21T16:21:35.138+08:00[Asia/Shanghai]","screenshots":[{"screenshot":"a269add09a1a53ad981883a6071876c0611ddbff976faeffca255474bce059db.png","timeStamp":1676967726138},{"screenshot":"d98cc8bf65f41c2f0a21ce8844aab1d83f0bce05e441eb245c7dcc7436f434a9.png","timeStamp":1676967726867},{"screenshot":"6deed877421e07a25f9a90f0d2a34724e9c721079d22a7a7da0bd7991dcee364.png","timeStamp":1676967729041}],"result":"SUCCESS","precondition":false,"level":0},{"number":10,"description":"When I set the Gross Amount to \u002710000\u0027","duration":3858,"startTime":"2023-02-21T16:22:09.042+08:00[Asia/Shanghai]","screenshots":[{"screenshot":"6e835e332c7d6442d381b4f00e26f9e63fd3567f896e83a3d8e40648f9a3b4d4.png","timeStamp":1676967732900}],"result":"SUCCESS","precondition":false,"level":0},{"number":11,"description":"When I set the Payment Terms to \u002730\u0027","duration":5797,"startTime":"2023-02-21T16:22:12.900+08:00[Asia/Shanghai]","screenshots":[{"screenshot":"1ca7a150273d34007493bd2d4958a2cc86c4abf94b24da991312ecbda0d00125.png","timeStamp":1676967733766},{"screenshot":"42b538ff3a62f41bafa3b785dfccfe0d7146ac8218d4f113548cd6dbe3ace170.png","timeStamp":1676967737609},{"screenshot":"c91ca18f952a3d72c4e926c22fb17116f8f9eb2aae8d918df098b1438f4f058d.png","timeStamp":1676967738697}],"result":"SUCCESS","precondition":false,"level":0},{"number":12,"description":"When I set the Tax Area to \u0027KF7\u0027","duration":11138,"startTime":"2023-02-21T16:22:18.698+08:00[Asia/Shanghai]","screenshots":[{"screenshot":"ff2cdb1499fd6e769f5b47a7a53c73129efc42eeb3d4302a4df25cb9022d7c31.png","timeStamp":1676967743157},{"screenshot":"661a20f93d21ed029a1c1c9850a0168ea1858cc5a3a5d2da4dfad084a27a9724.png","timeStamp":1676967745535},{"screenshot":"f8ba218b907b9c511fedc80c603ac0040656db1c3613d4d4d85b5563c3cf1a80.png","timeStamp":1676967749836}],"result":"SUCCESS","precondition":false,"level":0,"children":[{"number":13,"description":"When i click the last payment amount table row if its not editable","duration":3535,"startTime":"2023-02-21T16:22:18.714+08:00[Asia/Shanghai]","screenshots":[{"screenshot":"8139be7888b7b869628788fbfc14a244d6f208f7db6bef1c9cd8d2837f5bb74d.png","timeStamp":1676967742249}],"result":"SUCCESS","precondition":false,"level":1}]},{"number":14,"description":"Then the tax amount of the first line should be filled out","duration":616,"startTime":"2023-02-21T16:22:29.837+08:00[Asia/Shanghai]","screenshots":[{"screenshot":"f8ba218b907b9c511fedc80c603ac0040656db1c3613d4d4d85b5563c3cf1a80.png","timeStamp":1676967750453}],"result":"SUCCESS","precondition":false,"level":0},{"number":15,"description":"When i click on continue button","duration":2115,"startTime":"2023-02-21T16:22:30.454+08:00[Asia/Shanghai]","screenshots":[{"screenshot":"3897f5709d137c9dd3cfd049ecfe1be8e48bc395199f0ee09652c47a3d9c450c.png","timeStamp":1676967751095},{"screenshot":"0e52c0c96abc2601b1fa9a47cdc5e1b0134ea037eab5248a2ff9205d4d7d00e8.png","timeStamp":1676967752569}],"result":"SUCCESS","precondition":false,"level":0},{"number":16,"description":"Then the \u0027GL Distribution\u0027 form and its contents should show up","duration":377,"startTime":"2023-02-21T16:22:32.570+08:00[Asia/Shanghai]","screenshots":[{"screenshot":"eaa980cc7da7ec58afb21dd1d939042a8e222d0582a62099779541a28d29b1b9.png","timeStamp":1676967752947}],"result":"SUCCESS","precondition":false,"level":0},{"number":17,"description":"When I fill up the last row line using Account Number: \u0027960001\u0027, Line Description: \u0027TEST1\u0027, Amount: \u00271000\u0027, Cost Center: \u0027DAV2000\u0027, Gen Obj: \u0027AFGHAIG\u0027, AOE: \u0027YAO\u0027, Line Ref: \u0027Test1\u0027, Units: \u002721\u0027","duration":61435,"startTime":"2023-02-21T16:22:32.948+08:00[Asia/Shanghai]","screenshots":[{"screenshot":"b787c4e7571b6652b6c94909cc9136831e8bfeb27acc94bf9d09bd6a2b6782b7.png","timeStamp":1676967814383}],"result":"SUCCESS","precondition":false,"level":0,"children":[{"number":18,"description":"When I click the last \u0027Additional Lines\u0027 table row","duration":3878,"startTime":"2023-02-21T16:22:32.961+08:00[Asia/Shanghai]","screenshots":[{"screenshot":"bc454467354a1674d454761b6e17f9f7debebe14fda496bdcd244edf690d734e.png","timeStamp":1676967753538},{"screenshot":"7916cc3625e4f413a92d2496d2012434631409dc66d13df0723c685239d753eb.png","timeStamp":1676967756839}],"result":"SUCCESS","precondition":false,"level":1},{"number":19,"description":"When I set the \u0027Account Number\u0027 to \u0027960001\u0027","duration":7558,"startTime":"2023-02-21T16:22:36.840+08:00[Asia/Shanghai]","screenshots":[{"screenshot":"7916cc3625e4f413a92d2496d2012434631409dc66d13df0723c685239d753eb.png","timeStamp":1676967756852},{"screenshot":"829d6ad5c86af922c43a8c6f4309d3da5299ee7dce57368ed068e812660fb022.png","timeStamp":1676967759907},{"screenshot":"1ad4eb26f1509914e03eacb55d97e8cbb5d420b0c8f0816f713a7d619c6efed8.png","timeStamp":1676967764398}],"result":"SUCCESS","precondition":false,"level":1},{"number":20,"description":"Then the Line Description placeholder should be set to \u0027PREMISE CODE/Consumption Period\u0027","duration":538,"startTime":"2023-02-21T16:22:44.399+08:00[Asia/Shanghai]","screenshots":[{"screenshot":"1ad4eb26f1509914e03eacb55d97e8cbb5d420b0c8f0816f713a7d619c6efed8.png","timeStamp":1676967764413},{"screenshot":"c73faeb6c4ce28f46c29e42a68fd20346bab3aadc2ebf4a700011490b2355ca5.png","timeStamp":1676967764937}],"result":"SUCCESS","precondition":false,"level":1},{"number":21,"description":"When I set the \u0027Line Description\u0027 to \u0027TEST1\u0027","duration":4367,"startTime":"2023-02-21T16:22:44.938+08:00[Asia/Shanghai]","screenshots":[{"screenshot":"c73faeb6c4ce28f46c29e42a68fd20346bab3aadc2ebf4a700011490b2355ca5.png","timeStamp":1676967764950},{"screenshot":"8fb0dbb4c77c8d3cf9f9b46812d351d3bb721861c14f484d22d5c8c28efb481c.png","timeStamp":1676967769305}],"result":"SUCCESS","precondition":false,"level":1},{"number":22,"description":"When I set the \u0027Amount\u0027 to \u00271000\u0027","duration":7423,"startTime":"2023-02-21T16:22:49.306+08:00[Asia/Shanghai]","screenshots":[{"screenshot":"8fb0dbb4c77c8d3cf9f9b46812d351d3bb721861c14f484d22d5c8c28efb481c.png","timeStamp":1676967769322},{"screenshot":"c7648336c357caf47e08eb5681cd8541a7f1afbaea2de30389f5c51ae12159df.png","timeStamp":1676967776729}],"result":"SUCCESS","precondition":false,"level":1},{"number":23,"description":"When I set the \u0027Cost Center\u0027 to \u0027DAV2000\u0027","duration":7833,"startTime":"2023-02-21T16:22:56.730+08:00[Asia/Shanghai]","screenshots":[{"screenshot":"c7648336c357caf47e08eb5681cd8541a7f1afbaea2de30389f5c51ae12159df.png","timeStamp":1676967776741},{"screenshot":"f4c6a1af1181dfd86f344afa7492b1d23171e4ec772aa0329f65a4deea38efe3.png","timeStamp":1676967779979},{"screenshot":"b2ec941e0ff5fcc34bb0dd7d0a4a23d433b2cf508e65081a3ef476399531093a.png","timeStamp":1676967784563}],"result":"SUCCESS","precondition":false,"level":1},{"number":24,"description":"When I set the \u0027Gen Obj\u0027 to \u0027AFGHAIG\u0027","duration":8079,"startTime":"2023-02-21T16:23:04.564+08:00[Asia/Shanghai]","screenshots":[{"screenshot":"b2ec941e0ff5fcc34bb0dd7d0a4a23d433b2cf508e65081a3ef476399531093a.png","timeStamp":1676967784575},{"screenshot":"565afea6f78f10394f01d70fac6154ce3ee518dadff52cf32eaab8b54e73e855.png","timeStamp":1676967788243},{"screenshot":"7d7ea1fe6cd0d70bd58a0a4d9e1b624bea077bd3b86b8ef48304febb1cb4dd92.png","timeStamp":1676967792643}],"result":"SUCCESS","precondition":false,"level":1},{"number":25,"description":"When I click on \u0027Show Next\u0027 button","duration":3904,"startTime":"2023-02-21T16:23:12.643+08:00[Asia/Shanghai]","screenshots":[{"screenshot":"7d7ea1fe6cd0d70bd58a0a4d9e1b624bea077bd3b86b8ef48304febb1cb4dd92.png","timeStamp":1676967792655},{"screenshot":"c609ed30ffdeb151d11285e91508876194611decf30dd0bde48b38099698be17.png","timeStamp":1676967793256},{"screenshot":"b2d07d9f1293ad59851565402a9cf1dfd4bf34230c7208666996417313da909a.png","timeStamp":1676967796547}],"result":"SUCCESS","precondition":false,"level":1},{"number":26,"description":"When I set the \u0027AOE\u0027 to \u0027YAO\u0027","duration":7730,"startTime":"2023-02-21T16:23:16.547+08:00[Asia/Shanghai]","screenshots":[{"screenshot":"b2d07d9f1293ad59851565402a9cf1dfd4bf34230c7208666996417313da909a.png","timeStamp":1676967796558},{"screenshot":"be156993a87a1d4d5a4fb3605baa455e08db439c1c53fb12ce7c26c5a72bd16a.png","timeStamp":1676967799851},{"screenshot":"d3e93c6cb034d7ec8d359b282cea8e516a430fe6a3ef74f949975fe9a6b6318c.png","timeStamp":1676967804277}],"result":"SUCCESS","precondition":false,"level":1},{"number":27,"description":"When I set the \u0027Units\u0027 to \u002721\u0027","duration":4390,"startTime":"2023-02-21T16:23:24.278+08:00[Asia/Shanghai]","screenshots":[{"screenshot":"d3e93c6cb034d7ec8d359b282cea8e516a430fe6a3ef74f949975fe9a6b6318c.png","timeStamp":1676967804289},{"screenshot":"b4e6a317521b6c3e7849bd15dcd5d2851c806cd82af13bad5a6576d51e38d7ee.png","timeStamp":1676967808668}],"result":"SUCCESS","precondition":false,"level":1},{"number":28,"description":"Then the Unit of Measure should be set to \u0027Cubic Metre\u0027","duration":586,"startTime":"2023-02-21T16:23:28.668+08:00[Asia/Shanghai]","screenshots":[{"screenshot":"b4e6a317521b6c3e7849bd15dcd5d2851c806cd82af13bad5a6576d51e38d7ee.png","timeStamp":1676967808679},{"screenshot":"f72e3aa56f7bc92142b7c7fccae0216c74e11fa59dd8ceb00a5a21e3f53f3435.png","timeStamp":1676967809254}],"result":"SUCCESS","precondition":false,"level":1},{"number":29,"description":"When I set the \u0027AOE\u0027 to \u0027Test1\u0027","duration":4516,"startTime":"2023-02-21T16:23:29.255+08:00[Asia/Shanghai]","screenshots":[{"screenshot":"f72e3aa56f7bc92142b7c7fccae0216c74e11fa59dd8ceb00a5a21e3f53f3435.png","timeStamp":1676967809267},{"screenshot":"95f21502710b3a3b5ddeb1277d0568ee36ce38f47983624fcff8f648eaa84595.png","timeStamp":1676967813771}],"result":"SUCCESS","precondition":false,"level":1},{"number":30,"description":"When I click on \u0027Show Previous\u0027 button","duration":600,"startTime":"2023-02-21T16:23:33.772+08:00[Asia/Shanghai]","screenshots":[{"screenshot":"95f21502710b3a3b5ddeb1277d0568ee36ce38f47983624fcff8f648eaa84595.png","timeStamp":1676967813784},{"screenshot":"b787c4e7571b6652b6c94909cc9136831e8bfeb27acc94bf9d09bd6a2b6782b7.png","timeStamp":1676967814360},{"screenshot":"b787c4e7571b6652b6c94909cc9136831e8bfeb27acc94bf9d09bd6a2b6782b7.png","timeStamp":1676967814372}],"result":"SUCCESS","precondition":false,"level":1}]},{"number":31,"description":"When I click \u0027Add Line\u0027 button","duration":627,"startTime":"2023-02-21T16:23:34.384+08:00[Asia/Shanghai]","screenshots":[{"screenshot":"deb26fea92d94cc42cc9c929058d842e8da2e614f61c5a8672f09faa049b2d41.png","timeStamp":1676967814999},{"screenshot":"deb26fea92d94cc42cc9c929058d842e8da2e614f61c5a8672f09faa049b2d41.png","timeStamp":1676967815011}],"result":"SUCCESS","precondition":false,"level":0},{"number":32,"description":"When I fill up the last row line using Account Number: \u0027960002\u0027, Line Description: \u0027TEST1\u0027, Amount: \u00271000\u0027, Cost Center: \u0027DAV2120\u0027, Gen Obj: \u0027AFGHAIG\u0027, AOE: \u0027YAO\u0027, Line Ref: \u0027Test1\u0027, Units: \u002710\u0027","duration":61398,"startTime":"2023-02-21T16:23:35.012+08:00[Asia/Shanghai]","screenshots":[{"screenshot":"8597f1935cfe252cbbec267cb69b8ed46669e748a51c6856dd8f3873fe17e4ad.png","timeStamp":1676967876410}],"result":"SUCCESS","precondition":false,"level":0,"children":[{"number":33,"description":"When I click the last \u0027Additional Lines\u0027 table row","duration":3908,"startTime":"2023-02-21T16:23:35.024+08:00[Asia/Shanghai]","screenshots":[{"screenshot":"02414d1162e096f990129fc965573d2571b938ce0f6b65a94fc24d7ba14cd2a8.png","timeStamp":1676967815640},{"screenshot":"7449856588c2c20307c62721e13a8e708103759b29509c9a2325510d8d87c135.png","timeStamp":1676967818932}],"result":"SUCCESS","precondition":false,"level":1},{"number":34,"description":"When I set the \u0027Account Number\u0027 to \u0027960002\u0027","duration":7859,"startTime":"2023-02-21T16:23:38.933+08:00[Asia/Shanghai]","screenshots":[{"screenshot":"7449856588c2c20307c62721e13a8e708103759b29509c9a2325510d8d87c135.png","timeStamp":1676967818945},{"screenshot":"85d78711610e0a079cfb40e84c27faf772f2254a65409454bc3beeab49d872e5.png","timeStamp":1676967821978},{"screenshot":"db525c5c4b2033380a569bfb86a832fce088509ef6e9a14c33c89966f8a79658.png","timeStamp":1676967826792}],"result":"SUCCESS","precondition":false,"level":1},{"number":35,"description":"Then the Line Description placeholder should be set to \u0027PREMISE CODE/Consumption Period\u0027","duration":530,"startTime":"2023-02-21T16:23:46.793+08:00[Asia/Shanghai]","screenshots":[{"screenshot":"db525c5c4b2033380a569bfb86a832fce088509ef6e9a14c33c89966f8a79658.png","timeStamp":1676967826807},{"screenshot":"2b7451c08e78df8f28dd60aea2f2c035f502bc0f8b02fc946a53efc1b49f63a5.png","timeStamp":1676967827323}],"result":"SUCCESS","precondition":false,"level":1},{"number":36,"description":"When I set the \u0027Line Description\u0027 to \u0027TEST1\u0027","duration":4324,"startTime":"2023-02-21T16:23:47.324+08:00[Asia/Shanghai]","screenshots":[{"screenshot":"2b7451c08e78df8f28dd60aea2f2c035f502bc0f8b02fc946a53efc1b49f63a5.png","timeStamp":1676967827334},{"screenshot":"200207d7d21a1ea6295afdd367cd77fa3a294737ba6a1029a14dfe94736ac752.png","timeStamp":1676967831648}],"result":"SUCCESS","precondition":false,"level":1},{"number":37,"description":"When I set the \u0027Amount\u0027 to \u00271000\u0027","duration":7382,"startTime":"2023-02-21T16:23:51.649+08:00[Asia/Shanghai]","screenshots":[{"screenshot":"200207d7d21a1ea6295afdd367cd77fa3a294737ba6a1029a14dfe94736ac752.png","timeStamp":1676967831660},{"screenshot":"c5b1c06d400361edca6eab91fd766447eaab10ea0350d6a1e5cd0ae560e20106.png","timeStamp":1676967839031}],"result":"SUCCESS","precondition":false,"level":1},{"number":38,"description":"When I set the \u0027Cost Center\u0027 to \u0027DAV2120\u0027","duration":7727,"startTime":"2023-02-21T16:23:59.031+08:00[Asia/Shanghai]","screenshots":[{"screenshot":"c5b1c06d400361edca6eab91fd766447eaab10ea0350d6a1e5cd0ae560e20106.png","timeStamp":1676967839043},{"screenshot":"e1c2e9bc3d9edc14bd2a73efc76277d009200e0419e620fad56c24b65d4734a7.png","timeStamp":1676967842303},{"screenshot":"7f6992ddaa5609ebf77ea8b7fa130898bc5f435e06cac0c66b546b1a43b02068.png","timeStamp":1676967846758}],"result":"SUCCESS","precondition":false,"level":1},{"number":39,"description":"When I set the \u0027Gen Obj\u0027 to \u0027AFGHAIG\u0027","duration":7661,"startTime":"2023-02-21T16:24:06.758+08:00[Asia/Shanghai]","screenshots":[{"screenshot":"7f6992ddaa5609ebf77ea8b7fa130898bc5f435e06cac0c66b546b1a43b02068.png","timeStamp":1676967846769},{"screenshot":"bb656551bef0eb2d1aff58c6d26b3c318a4f0b1c8d1ed7d39538b1ee522c9cce.png","timeStamp":1676967849992},{"screenshot":"dde1285b70f23eefd8841b89c982fac253607cecbc6cadb6045b8fd86c9cc65e.png","timeStamp":1676967854419}],"result":"SUCCESS","precondition":false,"level":1},{"number":40,"description":"When I click on \u0027Show Next\u0027 button","duration":3908,"startTime":"2023-02-21T16:24:14.420+08:00[Asia/Shanghai]","screenshots":[{"screenshot":"dde1285b70f23eefd8841b89c982fac253607cecbc6cadb6045b8fd86c9cc65e.png","timeStamp":1676967854432},{"screenshot":"c24d6e70d468e5fdafc9a56c132ebeb6fff860434669313da7e1626750de2ffd.png","timeStamp":1676967855035},{"screenshot":"94d3c8b4270deef4d63a36a613567696ccec336970fa2b3c65fd97c9e0197b04.png","timeStamp":1676967858328}],"result":"SUCCESS","precondition":false,"level":1},{"number":41,"description":"When I set the \u0027AOE\u0027 to \u0027YAO\u0027","duration":7865,"startTime":"2023-02-21T16:24:18.329+08:00[Asia/Shanghai]","screenshots":[{"screenshot":"94d3c8b4270deef4d63a36a613567696ccec336970fa2b3c65fd97c9e0197b04.png","timeStamp":1676967858339},{"screenshot":"cebdce8639251ffca1cc6083f2a3a0aa07e2436104d271be37c0a0a7b9de4beb.png","timeStamp":1676967861740},{"screenshot":"712d2b0298318a58bfbf8c0b29172df7a1b6c28e983e63aeb73f565445f905cf.png","timeStamp":1676967866194}],"result":"SUCCESS","precondition":false,"level":1},{"number":42,"description":"When I set the \u0027Units\u0027 to \u002710\u0027","duration":4391,"startTime":"2023-02-21T16:24:26.195+08:00[Asia/Shanghai]","screenshots":[{"screenshot":"712d2b0298318a58bfbf8c0b29172df7a1b6c28e983e63aeb73f565445f905cf.png","timeStamp":1676967866207},{"screenshot":"11123af692ffa06df2e055d18781c5b82f99c16bace60b7687ac5aff56e1c1b1.png","timeStamp":1676967870586}],"result":"SUCCESS","precondition":false,"level":1},{"number":43,"description":"Then the Unit of Measure should be set to \u0027Kilowatt Hour\u0027","duration":601,"startTime":"2023-02-21T16:24:30.587+08:00[Asia/Shanghai]","screenshots":[{"screenshot":"11123af692ffa06df2e055d18781c5b82f99c16bace60b7687ac5aff56e1c1b1.png","timeStamp":1676967870601},{"screenshot":"dc4066b595583040b0aa997cecbe9b289998108c8858cba6c5ae466b4a6c6c09.png","timeStamp":1676967871188}],"result":"SUCCESS","precondition":false,"level":1},{"number":44,"description":"When I set the \u0027AOE\u0027 to \u0027Test1\u0027","duration":4561,"startTime":"2023-02-21T16:24:31.189+08:00[Asia/Shanghai]","screenshots":[{"screenshot":"dc4066b595583040b0aa997cecbe9b289998108c8858cba6c5ae466b4a6c6c09.png","timeStamp":1676967871200},{"screenshot":"1f6858d5396e6da12f1f1b174d7aebec36bd44cc32806b853e7a3da4848bdb77.png","timeStamp":1676967875750}],"result":"SUCCESS","precondition":false,"level":1},{"number":45,"description":"When I click on \u0027Show Previous\u0027 button","duration":648,"startTime":"2023-02-21T16:24:35.751+08:00[Asia/Shanghai]","screenshots":[{"screenshot":"1f6858d5396e6da12f1f1b174d7aebec36bd44cc32806b853e7a3da4848bdb77.png","timeStamp":1676967875762},{"screenshot":"8597f1935cfe252cbbec267cb69b8ed46669e748a51c6856dd8f3873fe17e4ad.png","timeStamp":1676967876387},{"screenshot":"8597f1935cfe252cbbec267cb69b8ed46669e748a51c6856dd8f3873fe17e4ad.png","timeStamp":1676967876399}],"result":"SUCCESS","precondition":false,"level":1}]},{"number":46,"description":"When I click \u0027Add Line\u0027 button","duration":615,"startTime":"2023-02-21T16:24:36.411+08:00[Asia/Shanghai]","screenshots":[{"screenshot":"e00e28839c25ef5c8db5cda6d7139780b5a0c1e3df294135c7d9a66f1e41cb04.png","timeStamp":1676967877014},{"screenshot":"e00e28839c25ef5c8db5cda6d7139780b5a0c1e3df294135c7d9a66f1e41cb04.png","timeStamp":1676967877026}],"result":"SUCCESS","precondition":false,"level":0},{"number":47,"description":"When I fill up the last row line using Account Number: \u0027960003\u0027, Line Description: \u0027TEST1\u0027, Amount: \u00271000\u0027, Cost Center: \u0027AMM2100\u0027, Gen Obj: \u0027AFGHAIG\u0027, AOE: \u0027YAO\u0027, Line Ref: \u0027Test1\u0027, Units: \u002730\u0027","duration":62990,"startTime":"2023-02-21T16:24:37.027+08:00[Asia/Shanghai]","screenshots":[{"screenshot":"a07263de7a80cbc83a5ea818b04a21dee60be615addc54c35a6b57d34ed42f13.png","timeStamp":1676967940017}],"result":"SUCCESS","precondition":false,"level":0,"children":[{"number":48,"description":"When I click the last \u0027Additional Lines\u0027 table row","duration":3893,"startTime":"2023-02-21T16:24:37.039+08:00[Asia/Shanghai]","screenshots":[{"screenshot":"d1a1faa473e059c1af27c8c47c0b38d06180c794fe1224f569dc4e39cf199eed.png","timeStamp":1676967877649},{"screenshot":"b963f32a0900b32102a24e54181c7b781b555f64711954d7d440e6904842679b.png","timeStamp":1676967880932}],"result":"SUCCESS","precondition":false,"level":1},{"number":49,"description":"When I set the \u0027Account Number\u0027 to \u0027960003\u0027","duration":8041,"startTime":"2023-02-21T16:24:40.933+08:00[Asia/Shanghai]","screenshots":[{"screenshot":"b963f32a0900b32102a24e54181c7b781b555f64711954d7d440e6904842679b.png","timeStamp":1676967880945},{"screenshot":"0e619d5b81ba84f3966a5127023b5e7f98c8015ccfebf044fa3289a37047e7e8.png","timeStamp":1676967884210},{"screenshot":"3f77a7a4ddd451f26389de54f0038d0380442db2ac565c7984dea0728b0aaba2.png","timeStamp":1676967888974}],"result":"SUCCESS","precondition":false,"level":1},{"number":50,"description":"Then the Line Description placeholder should be set to \u0027PREMISE CODE/Consumption Period\u0027","duration":567,"startTime":"2023-02-21T16:24:48.975+08:00[Asia/Shanghai]","screenshots":[{"screenshot":"3f77a7a4ddd451f26389de54f0038d0380442db2ac565c7984dea0728b0aaba2.png","timeStamp":1676967888994},{"screenshot":"b47e1b6a17773fa1e437100502795e85079ef40d0f6917f1a69f897a40dc8fc7.png","timeStamp":1676967889542}],"result":"SUCCESS","precondition":false,"level":1},{"number":51,"description":"When I set the \u0027Line Description\u0027 to \u0027TEST1\u0027","duration":4450,"startTime":"2023-02-21T16:24:49.543+08:00[Asia/Shanghai]","screenshots":[{"screenshot":"b47e1b6a17773fa1e437100502795e85079ef40d0f6917f1a69f897a40dc8fc7.png","timeStamp":1676967889557},{"screenshot":"70556f00e50cbf50105b54c469e7a0f19c2523ca70e0ce4ab4a246476a8c052c.png","timeStamp":1676967893993}],"result":"SUCCESS","precondition":false,"level":1},{"number":52,"description":"When I set the \u0027Amount\u0027 to \u00271000\u0027","duration":7866,"startTime":"2023-02-21T16:24:53.994+08:00[Asia/Shanghai]","screenshots":[{"screenshot":"70556f00e50cbf50105b54c469e7a0f19c2523ca70e0ce4ab4a246476a8c052c.png","timeStamp":1676967894006},{"screenshot":"e343bae944204375773f65ee4d742608bed23e1a38f93c54048ae861c7df8c48.png","timeStamp":1676967901860}],"result":"SUCCESS","precondition":false,"level":1},{"number":53,"description":"When I set the \u0027Cost Center\u0027 to \u0027AMM2100\u0027","duration":7852,"startTime":"2023-02-21T16:25:01.861+08:00[Asia/Shanghai]","screenshots":[{"screenshot":"e343bae944204375773f65ee4d742608bed23e1a38f93c54048ae861c7df8c48.png","timeStamp":1676967901873},{"screenshot":"4f292982174e776490a8c02913c57f898f3b1d8a3b9e052921af8ed31ad82af8.png","timeStamp":1676967905108},{"screenshot":"8babbc193ba92efe5cb19addcbd27523df453c12304eca46bf4350d91f2e3f0c.png","timeStamp":1676967909713}],"result":"SUCCESS","precondition":false,"level":1},{"number":54,"description":"When I set the \u0027Gen Obj\u0027 to \u0027AFGHAIG\u0027","duration":7746,"startTime":"2023-02-21T16:25:09.713+08:00[Asia/Shanghai]","screenshots":[{"screenshot":"8babbc193ba92efe5cb19addcbd27523df453c12304eca46bf4350d91f2e3f0c.png","timeStamp":1676967909725},{"screenshot":"3fad9b1cd096cdaeb461ee77f39ed2f066356d98c287a0ba466a8a3269991c91.png","timeStamp":1676967913008},{"screenshot":"226cb1bdcde88b9528a5d7d2039cb816ed20cf576473df6bc6933a119fac01f6.png","timeStamp":1676967917459}],"result":"SUCCESS","precondition":false,"level":1},{"number":55,"description":"When I click on \u0027Show Next\u0027 button","duration":3914,"startTime":"2023-02-21T16:25:17.460+08:00[Asia/Shanghai]","screenshots":[{"screenshot":"226cb1bdcde88b9528a5d7d2039cb816ed20cf576473df6bc6933a119fac01f6.png","timeStamp":1676967917475},{"screenshot":"c24afafd403fce10f8440bc935de5473758eb6c62044d5c6703ae03f2da2c96b.png","timeStamp":1676967918059},{"screenshot":"d9b9575dcb15a8ee5cd1005957e7369a2722fe3d947c6e164ea3e4d3a62e5d11.png","timeStamp":1676967921374}],"result":"SUCCESS","precondition":false,"level":1},{"number":56,"description":"When I set the \u0027AOE\u0027 to \u0027YAO\u0027","duration":8402,"startTime":"2023-02-21T16:25:21.375+08:00[Asia/Shanghai]","screenshots":[{"screenshot":"d9b9575dcb15a8ee5cd1005957e7369a2722fe3d947c6e164ea3e4d3a62e5d11.png","timeStamp":1676967921386},{"screenshot":"bf279e8889d530a090c8940ba7e1e36403d1901534715850f9e207886c4bdb91.png","timeStamp":1676967924953},{"screenshot":"cf1bb12e5859fcebd0c15c1a708e998c4bac73d212450731e5a32859e36ec06d.png","timeStamp":1676967929777}],"result":"SUCCESS","precondition":false,"level":1},{"number":57,"description":"When I set the \u0027Units\u0027 to \u002730\u0027","duration":4386,"startTime":"2023-02-21T16:25:29.778+08:00[Asia/Shanghai]","screenshots":[{"screenshot":"cf1bb12e5859fcebd0c15c1a708e998c4bac73d212450731e5a32859e36ec06d.png","timeStamp":1676967929789},{"screenshot":"e77c9d8aa3ed049c21c31666fb5c8a1fec98b6b483376893ab2ff6cd63228968.png","timeStamp":1676967934164}],"result":"SUCCESS","precondition":false,"level":1},{"number":58,"description":"Then the Unit of Measure should be set to \u0027Cubic Metre\u0027","duration":599,"startTime":"2023-02-21T16:25:34.165+08:00[Asia/Shanghai]","screenshots":[{"screenshot":"e77c9d8aa3ed049c21c31666fb5c8a1fec98b6b483376893ab2ff6cd63228968.png","timeStamp":1676967934176},{"screenshot":"53e25e1d521fe14b4dd4595bf4e66ebbe9dcab2b5ff74ab70751492f3d4d5831.png","timeStamp":1676967934764}],"result":"SUCCESS","precondition":false,"level":1},{"number":59,"description":"When I set the \u0027AOE\u0027 to \u0027Test1\u0027","duration":4625,"startTime":"2023-02-21T16:25:34.765+08:00[Asia/Shanghai]","screenshots":[{"screenshot":"53e25e1d521fe14b4dd4595bf4e66ebbe9dcab2b5ff74ab70751492f3d4d5831.png","timeStamp":1676967934776},{"screenshot":"73ab65ea6a77a44adf6d2bdcd64cf5899431b8e0b87093904291c584fade259f.png","timeStamp":1676967939390}],"result":"SUCCESS","precondition":false,"level":1},{"number":60,"description":"When I click on \u0027Show Previous\u0027 button","duration":615,"startTime":"2023-02-21T16:25:39.391+08:00[Asia/Shanghai]","screenshots":[{"screenshot":"73ab65ea6a77a44adf6d2bdcd64cf5899431b8e0b87093904291c584fade259f.png","timeStamp":1676967939405},{"screenshot":"a07263de7a80cbc83a5ea818b04a21dee60be615addc54c35a6b57d34ed42f13.png","timeStamp":1676967939994},{"screenshot":"a07263de7a80cbc83a5ea818b04a21dee60be615addc54c35a6b57d34ed42f13.png","timeStamp":1676967940006}],"result":"SUCCESS","precondition":false,"level":1}]},{"number":61,"description":"When I click \u0027Add Line\u0027 button","duration":610,"startTime":"2023-02-21T16:25:40.018+08:00[Asia/Shanghai]","screenshots":[{"screenshot":"4a2ff0f156b887596b085ce4ea32a16a9f59cf099728be544f86fcd10fe7a8f2.png","timeStamp":1676967940616},{"screenshot":"4a2ff0f156b887596b085ce4ea32a16a9f59cf099728be544f86fcd10fe7a8f2.png","timeStamp":1676967940628}],"result":"SUCCESS","precondition":false,"level":0},{"number":62,"description":"When I fill up the last row line using Account Number: \u0027960004\u0027, Line Description: \u0027TEST1\u0027, Amount: \u00271000\u0027, Cost Center: \u0027DAM1000\u0027, Gen Obj: \u0027AFGHAIG\u0027, AOE: \u0027YAO\u0027, Line Ref: \u0027Test1\u0027, Units: \u002740\u0027","duration":61877,"startTime":"2023-02-21T16:25:40.629+08:00[Asia/Shanghai]","screenshots":[{"screenshot":"d8e79eb3439d97f0bc3497303531bde8b8e8a8dbd4e86b778fc01491307d0db6.png","timeStamp":1676968002506}],"result":"SUCCESS","precondition":false,"level":0,"children":[{"number":63,"description":"When I click the last \u0027Additional Lines\u0027 table row","duration":3962,"startTime":"2023-02-21T16:25:40.641+08:00[Asia/Shanghai]","screenshots":[{"screenshot":"38df350234399af635da4094c7af71bb225ff7c518d0e3fc3694f6f8a04b05f0.png","timeStamp":1676967941305},{"screenshot":"c39b57b50b7f7350cb6629f42f832f750e5583d37c1454d599bc2ef021e85c4c.png","timeStamp":1676967944603}],"result":"SUCCESS","precondition":false,"level":1},{"number":64,"description":"When I set the \u0027Account Number\u0027 to \u0027960004\u0027","duration":7810,"startTime":"2023-02-21T16:25:44.604+08:00[Asia/Shanghai]","screenshots":[{"screenshot":"c39b57b50b7f7350cb6629f42f832f750e5583d37c1454d599bc2ef021e85c4c.png","timeStamp":1676967944616},{"screenshot":"1d3ec52ef77cafa4caee9424a185c3bf9a947bec8b21257424517038fd9c9fa4.png","timeStamp":1676967947539},{"screenshot":"26067ea93498c2d0893a04e18835b22a4e0b497ec60310a20521885a2f8c0a20.png","timeStamp":1676967952414}],"result":"SUCCESS","precondition":false,"level":1},{"number":65,"description":"Then the Line Description placeholder should be set to \u0027PREMISE CODE/Consumption Period\u0027","duration":534,"startTime":"2023-02-21T16:25:52.415+08:00[Asia/Shanghai]","screenshots":[{"screenshot":"26067ea93498c2d0893a04e18835b22a4e0b497ec60310a20521885a2f8c0a20.png","timeStamp":1676967952426},{"screenshot":"27b3849900606a82cafdcc7c61e5f55eb400735cd24900160eb300013f4bf4d1.png","timeStamp":1676967952949}],"result":"SUCCESS","precondition":false,"level":1},{"number":66,"description":"When I set the \u0027Line Description\u0027 to \u0027TEST1\u0027","duration":4282,"startTime":"2023-02-21T16:25:52.949+08:00[Asia/Shanghai]","screenshots":[{"screenshot":"27b3849900606a82cafdcc7c61e5f55eb400735cd24900160eb300013f4bf4d1.png","timeStamp":1676967952961},{"screenshot":"678386df18433f87f9d1a70d2648b37197912a13be04708bee6fbf9b86c1d857.png","timeStamp":1676967957231}],"result":"SUCCESS","precondition":false,"level":1},{"number":67,"description":"When I set the \u0027Amount\u0027 to \u00271000\u0027","duration":7905,"startTime":"2023-02-21T16:25:57.232+08:00[Asia/Shanghai]","screenshots":[{"screenshot":"678386df18433f87f9d1a70d2648b37197912a13be04708bee6fbf9b86c1d857.png","timeStamp":1676967957245},{"screenshot":"750128a21c17c3f42f7b3c103d76a496b6e43a7bb6c0def6286bb8f7baa79e81.png","timeStamp":1676967965137}],"result":"SUCCESS","precondition":false,"level":1},{"number":68,"description":"When I set the \u0027Cost Center\u0027 to \u0027DAM1000\u0027","duration":7706,"startTime":"2023-02-21T16:26:05.138+08:00[Asia/Shanghai]","screenshots":[{"screenshot":"750128a21c17c3f42f7b3c103d76a496b6e43a7bb6c0def6286bb8f7baa79e81.png","timeStamp":1676967965150},{"screenshot":"e8418e3c374e5698d7dd91ac02e6b5cd5618badb41f58b611e5d18967586ca4d.png","timeStamp":1676967968396},{"screenshot":"8da1131f44c572dffbddea099ba36fc295aea1d6d8457ced019ca09fc001a05f.png","timeStamp":1676967972844}],"result":"SUCCESS","precondition":false,"level":1},{"number":69,"description":"When I set the \u0027Gen Obj\u0027 to \u0027AFGHAIG\u0027","duration":7778,"startTime":"2023-02-21T16:26:12.845+08:00[Asia/Shanghai]","screenshots":[{"screenshot":"8da1131f44c572dffbddea099ba36fc295aea1d6d8457ced019ca09fc001a05f.png","timeStamp":1676967972856},{"screenshot":"03c97f373aedf204ae93d0cf4f86e9a09d4fb82ad364619e3d849de45df4ab22.png","timeStamp":1676967976133},{"screenshot":"ea80c7c119b52a523affd8638a02c053d1bc463476b796454215ad7a167c86e6.png","timeStamp":1676967980623}],"result":"SUCCESS","precondition":false,"level":1},{"number":70,"description":"When I click on \u0027Show Next\u0027 button","duration":3939,"startTime":"2023-02-21T16:26:20.624+08:00[Asia/Shanghai]","screenshots":[{"screenshot":"ea80c7c119b52a523affd8638a02c053d1bc463476b796454215ad7a167c86e6.png","timeStamp":1676967980636},{"screenshot":"62e64daca1ed8b2e78bb30cad9a93009291218e16395e62a64250628fffcfba3.png","timeStamp":1676967981279},{"screenshot":"8a5685591871998fe38329e5567ff3d4a3064f4565143c91d880c8137058dadd.png","timeStamp":1676967984563}],"result":"SUCCESS","precondition":false,"level":1},{"number":71,"description":"When I set the \u0027AOE\u0027 to \u0027YAO\u0027","duration":7755,"startTime":"2023-02-21T16:26:24.563+08:00[Asia/Shanghai]","screenshots":[{"screenshot":"8a5685591871998fe38329e5567ff3d4a3064f4565143c91d880c8137058dadd.png","timeStamp":1676967984574},{"screenshot":"ceba121f0add850ed0d9ad76cd64c03a685b203e5ea42c3bb1611c212760aa03.png","timeStamp":1676967987927},{"screenshot":"80782b82b55c48f5a56635484bf48d634c6e71ab5f75583ef1b16152c0e53100.png","timeStamp":1676967992318}],"result":"SUCCESS","precondition":false,"level":1},{"number":72,"description":"When I set the \u0027Units\u0027 to \u002740\u0027","duration":4370,"startTime":"2023-02-21T16:26:32.319+08:00[Asia/Shanghai]","screenshots":[{"screenshot":"80782b82b55c48f5a56635484bf48d634c6e71ab5f75583ef1b16152c0e53100.png","timeStamp":1676967992330},{"screenshot":"aa1e853bffe11e2e88733d365409edce17c92f3215eb549b4659c454c7b8399e.png","timeStamp":1676967996689}],"result":"SUCCESS","precondition":false,"level":1},{"number":73,"description":"Then the Unit of Measure should be set to \u0027Giga Calories\u0027","duration":598,"startTime":"2023-02-21T16:26:36.690+08:00[Asia/Shanghai]","screenshots":[{"screenshot":"aa1e853bffe11e2e88733d365409edce17c92f3215eb549b4659c454c7b8399e.png","timeStamp":1676967996701},{"screenshot":"8667122880d5a44b1d2cfb2d38c221cef98cae37e88ea35086f249beb9e89561.png","timeStamp":1676967997288}],"result":"SUCCESS","precondition":false,"level":1},{"number":74,"description":"When I set the \u0027AOE\u0027 to \u0027Test1\u0027","duration":4576,"startTime":"2023-02-21T16:26:37.289+08:00[Asia/Shanghai]","screenshots":[{"screenshot":"8667122880d5a44b1d2cfb2d38c221cef98cae37e88ea35086f249beb9e89561.png","timeStamp":1676967997302},{"screenshot":"d21bfdc9876c92dcf8aaa76d28845f5e40753706acc9b836fe236bf49d15d5e0.png","timeStamp":1676968001865}],"result":"SUCCESS","precondition":false,"level":1},{"number":75,"description":"When I click on \u0027Show Previous\u0027 button","duration":629,"startTime":"2023-02-21T16:26:41.866+08:00[Asia/Shanghai]","screenshots":[{"screenshot":"d21bfdc9876c92dcf8aaa76d28845f5e40753706acc9b836fe236bf49d15d5e0.png","timeStamp":1676968001879},{"screenshot":"d8e79eb3439d97f0bc3497303531bde8b8e8a8dbd4e86b778fc01491307d0db6.png","timeStamp":1676968002483},{"screenshot":"d8e79eb3439d97f0bc3497303531bde8b8e8a8dbd4e86b778fc01491307d0db6.png","timeStamp":1676968002495}],"result":"SUCCESS","precondition":false,"level":1}]},{"number":76,"description":"When I click \u0027Add Line\u0027 button","duration":627,"startTime":"2023-02-21T16:26:42.507+08:00[Asia/Shanghai]","screenshots":[{"screenshot":"5f406914d9dbafbf3f113153e96a66c50d6756a86c763d4a6cacd6beb2dab373.png","timeStamp":1676968003122},{"screenshot":"5f406914d9dbafbf3f113153e96a66c50d6756a86c763d4a6cacd6beb2dab373.png","timeStamp":1676968003134}],"result":"SUCCESS","precondition":false,"level":0},{"number":77,"description":"When I fill up the last row line using Account Number: \u0027948001\u0027, Line Description: \u0027TEST1\u0027, Amount: \u0027\u003cnull\u003e\u0027, Cost Center: \u0027AMM2110\u0027, Gen Obj: \u0027AFGHAIG\u0027, AOE: \u0027YAO\u0027, Line Ref: \u0027Test1\u0027, Units: \u00271\u0027","duration":63041,"startTime":"2023-02-21T16:26:43.135+08:00[Asia/Shanghai]","screenshots":[{"screenshot":"8a5c3eb0184d9ede590bf9806bc981e3b6b866979cbbcd4808318bb8d34c9709.png","timeStamp":1676968066176}],"result":"SUCCESS","precondition":false,"level":0,"children":[{"number":78,"description":"When I click the last \u0027Additional Lines\u0027 table row","duration":3945,"startTime":"2023-02-21T16:26:43.148+08:00[Asia/Shanghai]","screenshots":[{"screenshot":"2108d079eeb38d3d82c4b4bf960250db1c899bbcab5ff2aaf4ef1f0cb14f2fc2.png","timeStamp":1676968003801},{"screenshot":"2b99aeb941523a364392585733fb6ac1f83197ed8604f068c40bf6bd873028f0.png","timeStamp":1676968007093}],"result":"SUCCESS","precondition":false,"level":1},{"number":79,"description":"When I set the \u0027Account Number\u0027 to \u0027948001\u0027","duration":7735,"startTime":"2023-02-21T16:26:47.094+08:00[Asia/Shanghai]","screenshots":[{"screenshot":"2b99aeb941523a364392585733fb6ac1f83197ed8604f068c40bf6bd873028f0.png","timeStamp":1676968007107},{"screenshot":"cb74b8b74253e63253ddb6f6f097a19e386a21b4f621137f38d53c35c5a932aa.png","timeStamp":1676968010118},{"screenshot":"1a9c86904a82e1ede40acea8b9a2619d3b998873a82aa1581e4c759c50a17be5.png","timeStamp":1676968014829}],"result":"SUCCESS","precondition":false,"level":1},{"number":80,"description":"Then the Line Description placeholder should be set to \u0027PREMISE CODE/Paper Size/Delivery Date\u0027","duration":542,"startTime":"2023-02-21T16:26:54.830+08:00[Asia/Shanghai]","screenshots":[{"screenshot":"1a9c86904a82e1ede40acea8b9a2619d3b998873a82aa1581e4c759c50a17be5.png","timeStamp":1676968014841},{"screenshot":"b764d56cf6682a735c1de3a9927b015afdd90c5dcfed69b26e43e5b5cf28cbe9.png","timeStamp":1676968015372}],"result":"SUCCESS","precondition":false,"level":1},{"number":81,"description":"When I set the \u0027Line Description\u0027 to \u0027TEST1\u0027","duration":4316,"startTime":"2023-02-21T16:26:55.373+08:00[Asia/Shanghai]","screenshots":[{"screenshot":"b764d56cf6682a735c1de3a9927b015afdd90c5dcfed69b26e43e5b5cf28cbe9.png","timeStamp":1676968015384},{"screenshot":"73c03c273d5664f1b494fe0e7475928785298b0aca842c186edfa8dfcf90bbf9.png","timeStamp":1676968019689}],"result":"SUCCESS","precondition":false,"level":1},{"number":82,"description":"When I set the \u0027Amount\u0027 to \u00275090.91\u0027","duration":8249,"startTime":"2023-02-21T16:26:59.790+08:00[Asia/Shanghai]","screenshots":[{"screenshot":"7e259e2bd8a6d7d13687ef75b17cad8d4700bd0e8fd45e3187bb37945234434e.png","timeStamp":1676968019973},{"screenshot":"fb9f3cae981166880e55ced8d75fa7dfdbf9b2b1dfa8c907c8aa9c066eda98a6.png","timeStamp":1676968028039}],"result":"SUCCESS","precondition":false,"level":1},{"number":83,"description":"When I set the \u0027Cost Center\u0027 to \u0027AMM2110\u0027","duration":7582,"startTime":"2023-02-21T16:27:08.040+08:00[Asia/Shanghai]","screenshots":[{"screenshot":"fb9f3cae981166880e55ced8d75fa7dfdbf9b2b1dfa8c907c8aa9c066eda98a6.png","timeStamp":1676968028055},{"screenshot":"25e4f32cd14e6a138babb9f83e08cbb02985de035a1a4fedc3566b81615784a9.png","timeStamp":1676968031199},{"screenshot":"dfc727fcd0ee40a66f8d2033d7bc486d942efa693d78985118b71da6d4b59b8c.png","timeStamp":1676968035622}],"result":"SUCCESS","precondition":false,"level":1},{"number":84,"description":"When I set the \u0027Gen Obj\u0027 to \u0027AFGHAIG\u0027","duration":8204,"startTime":"2023-02-21T16:27:15.623+08:00[Asia/Shanghai]","screenshots":[{"screenshot":"dfc727fcd0ee40a66f8d2033d7bc486d942efa693d78985118b71da6d4b59b8c.png","timeStamp":1676968035634},{"screenshot":"65d3b1274aa7041beee4e96b0c2b68ad52cd763548a75566cc304d3b47998c2d.png","timeStamp":1676968039417},{"screenshot":"f2088c3722d88f1cd791915a5e3e787e39799f5ad58c32ca0fb522ffd5cbe3e5.png","timeStamp":1676968043827}],"result":"SUCCESS","precondition":false,"level":1},{"number":85,"description":"When I click on \u0027Show Next\u0027 button","duration":3915,"startTime":"2023-02-21T16:27:23.828+08:00[Asia/Shanghai]","screenshots":[{"screenshot":"f2088c3722d88f1cd791915a5e3e787e39799f5ad58c32ca0fb522ffd5cbe3e5.png","timeStamp":1676968043839},{"screenshot":"0ae0a52fb0a1572fa58bfde1b7e1aa5edac5d75993624e144f73b4b33b5f6406.png","timeStamp":1676968044435},{"screenshot":"15e5a25d7eb9b4662aef0aaa5f519c2f8d0f2514f89b42657bbd4c1a7fb1ceaf.png","timeStamp":1676968047743}],"result":"SUCCESS","precondition":false,"level":1},{"number":86,"description":"When I set the \u0027AOE\u0027 to \u0027YAO\u0027","duration":8268,"startTime":"2023-02-21T16:27:27.743+08:00[Asia/Shanghai]","screenshots":[{"screenshot":"15e5a25d7eb9b4662aef0aaa5f519c2f8d0f2514f89b42657bbd4c1a7fb1ceaf.png","timeStamp":1676968047754},{"screenshot":"44b803a03f1fdad1cd7830dbef95b4c08a37cc6567505f8f46a28fdc8969ee9f.png","timeStamp":1676968051099},{"screenshot":"8feba13a34de6d05f935c66af8f5f4d56df0bf77f59062873a48f141d88513ae.png","timeStamp":1676968056011}],"result":"SUCCESS","precondition":false,"level":1},{"number":87,"description":"When I set the \u0027Units\u0027 to \u00271\u0027","duration":4360,"startTime":"2023-02-21T16:27:36.012+08:00[Asia/Shanghai]","screenshots":[{"screenshot":"8feba13a34de6d05f935c66af8f5f4d56df0bf77f59062873a48f141d88513ae.png","timeStamp":1676968056024},{"screenshot":"2d90dad2042e6f0f7bb0c623ad7a423851a78785114b5a37c3a6d78b63d13ec6.png","timeStamp":1676968060372}],"result":"SUCCESS","precondition":false,"level":1},{"number":88,"description":"Then the Unit of Measure should be set to \u0027Ream\u0027","duration":614,"startTime":"2023-02-21T16:27:40.373+08:00[Asia/Shanghai]","screenshots":[{"screenshot":"2d90dad2042e6f0f7bb0c623ad7a423851a78785114b5a37c3a6d78b63d13ec6.png","timeStamp":1676968060385},{"screenshot":"7e65e55057bae80f173a86f2c371d01a238c88152487e2473512ccc403983057.png","timeStamp":1676968060987}],"result":"SUCCESS","precondition":false,"level":1},{"number":89,"description":"When I set the \u0027AOE\u0027 to \u0027Test1\u0027","duration":4552,"startTime":"2023-02-21T16:27:40.988+08:00[Asia/Shanghai]","screenshots":[{"screenshot":"7e65e55057bae80f173a86f2c371d01a238c88152487e2473512ccc403983057.png","timeStamp":1676968061000},{"screenshot":"0226312af95b077095f6ad3ba0980727f3825d72b7e287eaa4dff428fbbb199d.png","timeStamp":1676968065540}],"result":"SUCCESS","precondition":false,"level":1},{"number":90,"description":"When I click on \u0027Show Previous\u0027 button","duration":624,"startTime":"2023-02-21T16:27:45.541+08:00[Asia/Shanghai]","screenshots":[{"screenshot":"0226312af95b077095f6ad3ba0980727f3825d72b7e287eaa4dff428fbbb199d.png","timeStamp":1676968065552},{"screenshot":"8a5c3eb0184d9ede590bf9806bc981e3b6b866979cbbcd4808318bb8d34c9709.png","timeStamp":1676968066151},{"screenshot":"8a5c3eb0184d9ede590bf9806bc981e3b6b866979cbbcd4808318bb8d34c9709.png","timeStamp":1676968066165}],"result":"SUCCESS","precondition":false,"level":1}]},{"number":91,"description":"When I click on \u0027Save\u0027 button","duration":4667,"startTime":"2023-02-21T16:27:46.176+08:00[Asia/Shanghai]","screenshots":[{"screenshot":"dd74f12f5ed7c5ea0f62e814f7ea67aa558da131d47382ea6637209a9f3ec744.png","timeStamp":1676968066836},{"screenshot":"0e71b2b2b1f246a798670c4097caa2bab378d214f734383bdd906b87c6e0fc23.png","timeStamp":1676968070843}],"result":"SUCCESS","precondition":false,"level":0},{"number":92,"description":"Then the voucher entry successfully created modal and its contents should show up","duration":1732,"startTime":"2023-02-21T16:27:50.845+08:00[Asia/Shanghai]","screenshots":[{"screenshot":"d320d66fad1b9bd2f060553197a3a459cfc0fa490f949d7791c6e98bb0b02a03.png","timeStamp":1676968072577}],"result":"SUCCESS","precondition":false,"level":0,"children":[{"number":93,"description":"Then the voucher entry successfully created modal should show up","duration":516,"startTime":"2023-02-21T16:27:50.866+08:00[Asia/Shanghai]","screenshots":[{"screenshot":"555a97d634200a95a0e885a7c42c568044be8b6599ff6a5a89446d9b3eab3c19.png","timeStamp":1676968071382}],"result":"SUCCESS","precondition":false,"level":1},{"number":94,"description":"Then the batch number from voucher entry successfully created modal should show up","duration":635,"startTime":"2023-02-21T16:27:51.387+08:00[Asia/Shanghai]","screenshots":[{"screenshot":"555a97d634200a95a0e885a7c42c568044be8b6599ff6a5a89446d9b3eab3c19.png","timeStamp":1676968071411},{"screenshot":"a39247cda6b7ab85601ba433cb2e39be90a1a8d36a5ec32c985b75dd72c9c448.png","timeStamp":1676968072022}],"result":"SUCCESS","precondition":false,"level":1},{"number":95,"description":"Then the document number from voucher entry successfully created modal should show up","duration":534,"startTime":"2023-02-21T16:27:52.023+08:00[Asia/Shanghai]","screenshots":[{"screenshot":"a39247cda6b7ab85601ba433cb2e39be90a1a8d36a5ec32c985b75dd72c9c448.png","timeStamp":1676968072049},{"screenshot":"d320d66fad1b9bd2f060553197a3a459cfc0fa490f949d7791c6e98bb0b02a03.png","timeStamp":1676968072557}],"result":"SUCCESS","precondition":false,"level":1}]}],"userStory":{"id":"org.icrc.fadapplic.IRIS.FAD.AccountsPayable.VoucherEntries","storyName":"Voucher entries","storyClassName":"org.icrc.fadapplic.IRIS.FAD.AccountsPayable.VoucherEntries","path":"FAD.AccountsPayable","type":"story"},"featureTag":{"name":"Accounts payable/Voucher entries","type":"story","displayName":"Accounts payable/Voucher entries"},"title":"Create voucher entry using sustainability accounts","coreIssues":["SPRINT7"],"tags":[{"name":"FAD/Accounts payable","type":"feature","displayName":"Accounts payable"},{"name":"FAD","type":"capability","displayName":"FAD"},{"name":"Accounts payable/Voucher entries","type":"story","displayName":"Voucher entries"}],"startTime":"2023-02-21T16:20:42.382+08:00[Asia/Shanghai]","duration":430196,"projectKey":"","sessionId":"c5707d938c6e43dc61ce7695507d6575","driver":"chrome","isManualTestingUpToDate":false,"manual":false,"testSource":"JUnit","result":"SUCCESS","issues":["SPRINT7"]}